pychannels/__init__.py
pychannels-1.2.3.dist-info/LICENSE
pychannels-1.2.3.dist-info/METADATA
pychannels-1.2.3.dist-info/WHEEL
pychannels-1.2.3.dist-info/top_level.txt
pychannels-1.2.3.dist-info/zip-safe
pychannels-1.2.3.dist-info/RECORD
