Metadata-Version: 2.1
Name: pychannels
Version: 1.2.3
Summary: API client for the Channels app - https://getchannels.com
Home-page: https://github.com/fancybits/pychannels
Author: Fancy Bits, LLC
Author-email: jon@getchannels.com
License: The MIT License
Keywords: api,client,channels,automation
Platform: UNKNOWN
